mm_cryptocurrency/__init__.py
mm_cryptocurrency/account.py
mm_cryptocurrency/calcs.py
mm_cryptocurrency/config.py
mm_cryptocurrency/log.py
mm_cryptocurrency/network.py
mm_cryptocurrency/node.py
mm_cryptocurrency/proxy.py
mm_cryptocurrency/py.typed
mm_cryptocurrency/retry.py
mm_cryptocurrency/utils.py
mm_cryptocurrency/validators.py
mm_cryptocurrency-0.4.7.dist-info/METADATA
mm_cryptocurrency-0.4.7.dist-info/WHEEL
mm_cryptocurrency-0.4.7.dist-info/RECORD
