Metadata-Version: 2.4
Name: mm-cryptocurrency
Version: 0.4.7
Requires-Python: >=3.13
Requires-Dist: loguru>=0.7.3
Requires-Dist: mm-http>=0.0.3
Requires-Dist: mm-print~=0.1.1
Requires-Dist: mm-result>=0.0.4
